datetime.py
setup.py
micropython_datetime.egg-info/PKG-INFO
micropython_datetime.egg-info/SOURCES.txt
micropython_datetime.egg-info/dependency_links.txt
micropython_datetime.egg-info/top_level.txt