Metadata-Version: 1.0
Name: micropython-datetime
Version: 0.0.1
Summary: Dummy datetime module for MicroPython
Home-page: https://github.com/micropython/micropython/issues/405
Author: MicroPython Developers
Author-email: micro-python@googlegroups.com
License: MIT
Platform: UNKNOWN
